[
  {
    "employer": "ELC MANAGEMENT LLC",
    "state": "NY",
    "city": "LONG ISLAND CITY"
  },
  {
    "employer": "ELDEC AEROSPACE CORP",
    "state": "WA",
    "city": "LYNNWOOD"
  },
  {
    "employer": "ELECTION SYSTEMS SOFTWARE LLC",
    "state": "NE",
    "city": "OMAHA"
  },
  {
    "employer": "ELECTRA VEHICLES INC",
    "state": "MA",
    "city": "BOSTON"
  },
  {
    "employer": "ELECTRATECT INC",
    "state": "AZ",
    "city": "PHOENIX"
  },
  {
    "employer": "ELECTRI TECH SERVICES INC",
    "state": "CA",
    "city": "CITY INDUSTRY"
  },
  {
    "employer": "ELECTRIC HYDROGEN CO",
    "state": "",
    "city": ""
  },
  {
    "employer": "ELECTRIC POWER BOARD OF CHATTANOOGA",
    "state": "TN",
    "city": "CHATTANOOGA"
  },
  {
    "employer": "ELECTRIC POWER ENGINEERS LLC",
    "state": "TX",
    "city": "AUSTIN"
  },
  {
    "employer": "ELECTRIC POWER GROUP LLC",
    "state": "CA",
    "city": "PASADENA"
  },
  {
    "employer": "ELECTRIC POWER RESEARCH INSTITUTE INC EPRI",
    "state": "",
    "city": ""
  },
  {
    "employer": "ELECTRIC POWER SYSTEMS INC",
    "state": "UT",
    "city": "NORTH LOGAN"
  },
  {
    "employer": "ELECTRIC RELIABILITY COUNCIL OF TEXAS INC ERCOT",
    "state": "TX",
    "city": "TAYLOR"
  },
  {
    "employer": "ELECTRIC SHEEP ROBOTICS INC",
    "state": "CA",
    "city": "SAN ANSELMO"
  },
  {
    "employer": "ELECTROLUX HOME PRODUCTS INC",
    "state": "NC",
    "city": "CHARLOTTE"
  },
  {
    "employer": "ELECTRONIC ARTS INC",
    "state": "CA",
    "city": "REDWOOD CITY"
  },
  {
    "employer": "ELECTRONIC ARTS TIBURON A FLORIDA CORPORATION",
    "state": "CA",
    "city": "REDWOOD CITY"
  },
  {
    "employer": "ELECTRONIC COOLING SOLUTIONS INC",
    "state": "CA",
    "city": "SANTA CLARA"
  },
  {
    "employer": "ELECTRONIC EVOLUTION TECHNOLOGIES INC",
    "state": "NV",
    "city": "RENO"
  },
  {
    "employer": "ELECTRONIC INTERCONNECT CORPORATION",
    "state": "IL",
    "city": "ELK GROVE VILLAGE"
  },
  {
    "employer": "ELECTRONIC WARNING TECHNOLOGIES LLC",
    "state": "MI",
    "city": "CADILLAC"
  },
  {
    "employer": "ELECTRONICS FOR IMAGING INC",
    "state": "CA",
    "city": "FREMONT"
  },
  {
    "employer": "ELEKTA INC",
    "state": "GA",
    "city": "ATLANTA"
  },
  {
    "employer": "ELEKTROBIT AUTOMOTIVE AMERICAS INC",
    "state": "MI",
    "city": "FARMINGTON HILLS"
  },
  {
    "employer": "ELEMENT ANALYTICS INC",
    "state": "CA",
    "city": "OAKLAND"
  },
  {
    "employer": "ELEMENT BIOSCIENCES INC",
    "state": "CA",
    "city": "SAN DIEGO"
  },
  {
    "employer": "ELEMENT BOX INC",
    "state": "TX",
    "city": "HOUSTON"
  },
  {
    "employer": "ELEMENT CAPITAL MANAGEMENT LLC",
    "state": "NY",
    "city": "NEW YORK"
  },
  {
    "employer": "ELEMENT ENERGY INC",
    "state": "CA",
    "city": "MENLO PARK"
  },
  {
    "employer": "ELEMENT FLEET CORPORATION",
    "state": "MD",
    "city": "SPARKS"
  },
  {
    "employer": "ELEMENT INC",
    "state": "NY",
    "city": "NEW YORK"
  },
  {
    "employer": "ELEMENT MATERIALS TECHNOLOGY DALLAS INC D/B/A AIRCOM INTERNATIONAL",
    "state": "TX",
    "city": "CARROLLTON"
  },
  {
    "employer": "ELEMENT SOLUTIONS INC",
    "state": "CT",
    "city": "WATERBURY"
  },
  {
    "employer": "ELEMENT STRUCTURAL ENGINEERS INC",
    "state": "CA",
    "city": "NEWARK"
  },
  {
    "employer": "ELEMENT TECHNOLOGIES INC",
    "state": "NJ",
    "city": "PISCATAWAY"
  },
  {
    "employer": "ELEMENT5 INC",
    "state": "CA",
    "city": "SAN JOSE"
  },
  {
    "employer": "ELEMENTAL TECHNOLOGIES LLC",
    "state": "VA",
    "city": "ARLINGTON"
  },
  {
    "employer": "ELEMENTS ACADEMY INC",
    "state": "MA",
    "city": "QUINCY"
  },
  {
    "employer": "ELEMENTS CONNECT LLC",
    "state": "NJ",
    "city": "MAHWAH"
  },
  {
    "employer": "ELEMICA INC FORMERLY PROCESSWEAVER INC",
    "state": "PA",
    "city": "WAYNE"
  },
  {
    "employer": "ELEPHANT INSURANCE SERVICES LLC",
    "state": "VA",
    "city": "HENRICO"
  },
  {
    "employer": "ELEPHAS BIOSCIENCES CORPORATION",
    "state": "WI",
    "city": "MADISON"
  },
  {
    "employer": "ELEVANCE HEALTH INC",
    "state": "IN",
    "city": "INDIANAPOLIS"
  },
  {
    "employer": "ELEVATE CREDIT SERVICE LLC",
    "state": "TX",
    "city": "FORT WORTH"
  },
  {
    "employer": "ELEVATE INNOVATION PARTNERS LLC",
    "state": "NY",
    "city": "NEW YORK"
  },
  {
    "employer": "ELEVATEBIO BASE CAMP INC",
    "state": "MA",
    "city": "WALTHAM"
  },
  {
    "employer": "ELEVATEBIO TECHNOLOGIES INC",
    "state": "MA",
    "city": "WALTHAM"
  },
  {
    "employer": "ELI LILLY AND COMPANY",
    "state": "IN",
    "city": "INDIANAPOLIS"
  },
  {
    "employer": "ELIASSEN GOVERNMENT SERVICES LLC",
    "state": "MD",
    "city": "BETHESDA"
  },
  {
    "employer": "ELIASSEN GROUP LLC",
    "state": "MA",
    "city": "READING"
  },
  {
    "employer": "ELICA HEALTH CENTERS",
    "state": "CA",
    "city": "SACRAMENTO"
  },
  {
    "employer": "ELICC AMERICAS CORPORATION",
    "state": "NY",
    "city": "NEW YORK"
  },
  {
    "employer": "ELICIO THERAPEUTICS INC",
    "state": "MA",
    "city": "BOSTON"
  },
  {
    "employer": "ELIM BIOPHARMACEUTICALS INC",
    "state": "CA",
    "city": "HAYWARD"
  },
  {
    "employer": "ELINK ELITE LLC",
    "state": "TX",
    "city": "TYLER"
  },
  {
    "employer": "ELIOT COMMUNITY HUMAN SERVICES INC",
    "state": "MA",
    "city": "LEXINGTON"
  },
  {
    "employer": "ELISITY INC",
    "state": "CA",
    "city": "SAN JOSE"
  },
  {
    "employer": "ELITE BIO REFERENCE LABORATORY INC",
    "state": "TX",
    "city": "HOUSTON"
  },
  {
    "employer": "ELITE BUSINESS CONSULTING LLC",
    "state": "VA",
    "city": "HERNDON"
  },
  {
    "employer": "ELITE EMANATE LLC",
    "state": "VA",
    "city": "LEESBURG"
  },
  {
    "employer": "ELITE EXCEED LLC",
    "state": "TX",
    "city": "IRVING"
  },
  {
    "employer": "ELITE INFOSYSTEMS INC",
    "state": "FL",
    "city": "WESLEY CHAPEL"
  },
  {
    "employer": "ELITE INNOVATIVE SOLUTIONS INC",
    "state": "TX",
    "city": "MCKINNEY"
  },
  {
    "employer": "ELITE MSO LLC",
    "state": "NJ",
    "city": "PRINCETON JUNCTION"
  },
  {
    "employer": "ELITE SOLUTIONS INC",
    "state": "GA",
    "city": "ATLANTA"
  },
  {
    "employer": "ELITE SPECIALTY CARE PC",
    "state": "NJ",
    "city": "SECAUCUS"
  },
  {
    "employer": "ELITE TECH INFO INC",
    "state": "TX",
    "city": "MCKINNEY"
  },
  {
    "employer": "ELITE TRANSIT SOLUTIONS LLC",
    "state": "PA",
    "city": "PITTSBURGH"
  },
  {
    "employer": "ELITEA GLOBAL CORP",
    "state": "IL",
    "city": "LAKE ZURICH"
  },
  {
    "employer": "ELIVATE AMERICA CORPORATION",
    "state": "NV",
    "city": "LAS VEGAS"
  },
  {
    "employer": "ELIX INC",
    "state": "MI",
    "city": "TROY"
  },
  {
    "employer": "ELIXIR DIAGNOSTICS LLC",
    "state": "",
    "city": ""
  },
  {
    "employer": "ELIXIR LAB USA INC DBA CARDINALITY",
    "state": "MD",
    "city": "POTOMAC"
  },
  {
    "employer": "ELIXIR MEDICAL CORPORATION",
    "state": "",
    "city": ""
  },
  {
    "employer": "ELIXIR TECHNICAL CONSULTING LLC",
    "state": "NJ",
    "city": "PRINCETON"
  },
  {
    "employer": "ELIXIR TECHNOLOGIES CORPORATION",
    "state": "CA",
    "city": "OJAI"
  },
  {
    "employer": "ELIZABETH PUBLIC SCHOOLS",
    "state": "NJ",
    "city": "ELIZABETH"
  },
  {
    "employer": "ELKEM SILICONES USA CORP",
    "state": "NJ",
    "city": "EAST BRUNSWICK"
  },
  {
    "employer": "ELLIANSE LLC",
    "state": "NV",
    "city": "HENDERSON"
  },
  {
    "employer": "ELLICIUM SOLUTIONS INC",
    "state": "CA",
    "city": "SANTA CLARA"
  },
  {
    "employer": "ELLIOT HOTEL INC DBA THE ELLIOT HOTEL",
    "state": "MA",
    "city": "BOSTON"
  },
  {
    "employer": "ELLIOTT COMPANY",
    "state": "",
    "city": ""
  },
  {
    "employer": "ELLIOTT MANAGEMENT CORPORATION",
    "state": "NY",
    "city": "NEW YORK"
  },
  {
    "employer": "ELLIQUENCE LLC",
    "state": "NY",
    "city": "BALDWIN"
  },
  {
    "employer": "ELLIS BANDT BIRKIN KOLLINS & WONG PLLC D/B/A DESERT RADIOLOGY",
    "state": "NV",
    "city": "HENDERSON"
  },
  {
    "employer": "ELLKAY LLC",
    "state": "NJ",
    "city": "ELMWOOD PARK"
  },
  {
    "employer": "ELLUCIAN COMPANY LP",
    "state": "",
    "city": ""
  },
  {
    "employer": "ELOCAL USA LLC",
    "state": "PA",
    "city": "CONSHOHOCKEN"
  },
  {
    "employer": "ELOGICSQUARE INC DBA ECLOUDWORKS",
    "state": "",
    "city": ""
  },
  {
    "employer": "ELOGISTEK LLC",
    "state": "CA",
    "city": "FONTANA"
  },
  {
    "employer": "ELON UNIVERSITY",
    "state": "NC",
    "city": "ELON"
  },
  {
    "employer": "ELRINGKLINGER SILICON VALLEY INC",
    "state": "CA",
    "city": "FREMONT"
  },
  {
    "employer": "ELROY AIR INC",
    "state": "CA",
    "city": "SOUTH SAN FRANCISCO"
  },
  {
    "employer": "ELSEVIER INC",
    "state": "GA",
    "city": "ALPHARETTA"
  },
  {
    "employer": "ELSIE WHITLOW STOKES CFPCS",
    "state": "DC",
    "city": "WASHINGTON"
  },
  {
    "employer": "ELTERNHAUS LLC",
    "state": "MD",
    "city": "DAYTON"
  },
  {
    "employer": "ELUCID BIOIMAGING INC",
    "state": "MA",
    "city": "BOSTON"
  },
  {
    "employer": "ELUMEN INC",
    "state": "MN",
    "city": "MINNEAPOLIS"
  },
  {
    "employer": "ELXR TECHNOLOGIES LLC",
    "state": "TX",
    "city": "FRISCO"
  },
  {
    "employer": "ELY SHOSHONE TRIBE",
    "state": "NV",
    "city": "ELY"
  }
]