[
  {
    "employer": "IFS NORTH AMERICA INC",
    "state": "IL",
    "city": "ITASCA"
  },
  {
    "employer": "IFUSION INC",
    "state": "NJ",
    "city": "HAMILTON"
  },
  {
    "employer": "IG US HOLDINGS INC",
    "state": "IL",
    "city": "CHICAGO"
  },
  {
    "employer": "IGATE SOLUTIONS LLC",
    "state": "TX",
    "city": "FRISCO"
  },
  {
    "employer": "IGAVEL INC",
    "state": "TX",
    "city": "NEW BRAUNFELS"
  },
  {
    "employer": "IGEN SYSTEMS LLC",
    "state": "NJ",
    "city": "WEST WINDSOR"
  },
  {
    "employer": "IGET SERVICES LLC",
    "state": "TX",
    "city": "HOUSTON"
  },
  {
    "employer": "IGM BIOSCIENCES INC.",
    "state": "CA",
    "city": "MOUNTAIN VIEW"
  },
  {
    "employer": "IGNITARIUM INC",
    "state": "TX",
    "city": "AUSTIN"
  },
  {
    "employer": "IGNITE IPA",
    "state": "NY",
    "city": "SAYVILLE"
  },
  {
    "employer": "IGNITE MEDICAL RESORT MCHENRY",
    "state": "IL",
    "city": "MCHENRY"
  },
  {
    "employer": "IGNITE SALES INC",
    "state": "TX",
    "city": "DALLAS"
  },
  {
    "employer": "IGNITION CREATIVE LLC",
    "state": "CA",
    "city": "LOS ANGELES"
  },
  {
    "employer": "IGPS LOGISTICS LLC",
    "state": "FL",
    "city": "ORLANDO"
  },
  {
    "employer": "IGROW VIRTUAL IT SOLUTIONS INC",
    "state": "TX",
    "city": "PLANO"
  },
  {
    "employer": "IGT",
    "state": "",
    "city": ""
  },
  {
    "employer": "IGT GLOBAL SOLUTIONS CORPORATION",
    "state": "RI",
    "city": "PROVIDENCE"
  },
  {
    "employer": "IGT TECHNOLOGIES INC",
    "state": "TN",
    "city": "KNOXVILLE"
  },
  {
    "employer": "IH ENGINEERS PC",
    "state": "NJ",
    "city": "PRINCETON"
  },
  {
    "employer": "IHA HEALTH SERVICES CORPORATION",
    "state": "MI",
    "city": "ANN ARBOR"
  },
  {
    "employer": "IHC HEALTH SERVICES INC DBA INTERMOUNTAIN HEALTHCARE",
    "state": "UT",
    "city": "MURRAY"
  },
  {
    "employer": "IHEALTH LABS INC",
    "state": "CA",
    "city": "SAN JOSE"
  },
  {
    "employer": "IHEARTMEDIA ENTERTAINMENT INC",
    "state": "TX",
    "city": "SAN ANTONIO"
  },
  {
    "employer": "IHEARTMEDIA MANAGEMENT SERVICES INC",
    "state": "TX",
    "city": "SAN ANTONIO"
  },
  {
    "employer": "IHERB LLC",
    "state": "CA",
    "city": "IRVINE"
  },
  {
    "employer": "IHI ENERGY SOLUTIONS INC",
    "state": "TX",
    "city": "HOUSTON"
  },
  {
    "employer": "IHRC INC",
    "state": "GA",
    "city": "ATLANTA"
  },
  {
    "employer": "IHS GLOBAL INC",
    "state": "NY",
    "city": "NEW YORK"
  },
  {
    "employer": "II VI OPTOELECTRONIC DEVICES INC",
    "state": "NJ",
    "city": "WARREN"
  },
  {
    "employer": "IIT JOBS INC",
    "state": "CA",
    "city": "SAN JOSE"
  },
  {
    "employer": "IKASYSTEMS A DELAWARE COMPANY DBA ADVANTASURE",
    "state": "MI",
    "city": "LANSING"
  },
  {
    "employer": "IKCON PHARMA INC",
    "state": "NJ",
    "city": "SOUTH PLAINFIELD"
  },
  {
    "employer": "IKCON TECHNOLOGIES INC",
    "state": "NJ",
    "city": "SOUTH PLAINFIELD"
  },
  {
    "employer": "IKNOWVATE TECHNOLOGIES INC",
    "state": "MI",
    "city": "SOUTHFIELD"
  },
  {
    "employer": "IKON SOFTWARE SERVICES",
    "state": "",
    "city": ""
  },
  {
    "employer": "IKON SYSTEMS LLC",
    "state": "TX",
    "city": "FRISCO"
  },
  {
    "employer": "IKON TECH SERVICES LLC",
    "state": "TX",
    "city": "HOUSTON"
  },
  {
    "employer": "IKONIC SOFT INC",
    "state": "MN",
    "city": "ROSEVILLE"
  },
  {
    "employer": "IKONIKA CORP",
    "state": "WA",
    "city": "FIFE"
  },
  {
    "employer": "IKRUSHER INC",
    "state": "CA",
    "city": "ARCADIA"
  },
  {
    "employer": "IKSANA CONSULTING LLC",
    "state": "NY",
    "city": "NEW YORK"
  },
  {
    "employer": "IL VENUS BUILDERS GROUP LLC",
    "state": "DC",
    "city": "WASHINGTON"
  },
  {
    "employer": "ILANTUS SERVICES PVT LIMITED",
    "state": "TX",
    "city": "PLANO"
  },
  {
    "employer": "ILANTUS SERVICES PVT LTD",
    "state": "TX",
    "city": "PLANO"
  },
  {
    "employer": "ILANTUS TECHNOLOGIES PVT LTD",
    "state": "",
    "city": ""
  },
  {
    "employer": "ILASZ AND ASSOCIATES",
    "state": "NY",
    "city": "NEW YORK"
  },
  {
    "employer": "ILIM COMMUNITY PARTNERS LLC",
    "state": "NC",
    "city": "CHARLOTTE"
  },
  {
    "employer": "ILINESOFT LLC",
    "state": "TX",
    "city": "SUGAR LAND"
  },
  {
    "employer": "ILINK SYSTEMS INC DBA ILINK DIGITAL",
    "state": "WA",
    "city": "BOTHELL"
  },
  {
    "employer": "ILJIN USA CORPORATION",
    "state": "MI",
    "city": "NOVI"
  },
  {
    "employer": "ILLINOIS INSTITUTE OF TECHNOLOGY",
    "state": "IL",
    "city": "CHICAGO"
  },
  {
    "employer": "ILLINOIS MUTUAL LIFE INSURANCE COMPANY",
    "state": "IL",
    "city": "PEORIA"
  },
  {
    "employer": "ILLINOIS STATE UNIVERSITY",
    "state": "",
    "city": ""
  },
  {
    "employer": "ILLINOIS TOOL WORKS INC",
    "state": "",
    "city": ""
  },
  {
    "employer": "ILLINOIS WESLEYAN UNIVERSITY",
    "state": "IL",
    "city": "BLOOMINGTON"
  },
  {
    "employer": "ILLUMIFIN CORPORATION",
    "state": "SC",
    "city": "GREENVILLE"
  },
  {
    "employer": "ILLUMINA INC",
    "state": "",
    "city": ""
  },
  {
    "employer": "ILLUMINATE TECHNOLOGIES LLC",
    "state": "VA",
    "city": "HERNDON"
  },
  {
    "employer": "ILLUMINE INVESTMENT MANAGEMENT LLC",
    "state": "WA",
    "city": "BAINBRIDGE ISLAND"
  },
  {
    "employer": "ILLUMIO INC",
    "state": "CA",
    "city": "SUNNYVALE"
  },
  {
    "employer": "ILMA CORPORATION DBA AIRPORT FOOD STORE",
    "state": "TX",
    "city": "HUMBLE"
  },
  {
    "employer": "ILOGIC INC",
    "state": "",
    "city": ""
  },
  {
    "employer": "ILOGIK INC",
    "state": "MA",
    "city": "WESTBOROUGH"
  },
  {
    "employer": "ILOGIXEDGE LLC",
    "state": "VA",
    "city": "HERNDON"
  },
  {
    "employer": "IM PRO MAKEUP NY LP",
    "state": "NY",
    "city": "NEW YORK"
  },
  {
    "employer": "IM SOLUTIONS INC",
    "state": "",
    "city": ""
  },
  {
    "employer": "IMAGE DIRECT GROUP LLC",
    "state": "MD",
    "city": "FREDERICK"
  },
  {
    "employer": "IMAGEN DENTAL PARTNERS LLC",
    "state": "AZ",
    "city": "SCOTTSDALE"
  },
  {
    "employer": "IMAGESCAN INC",
    "state": "CA",
    "city": "PASADENA"
  },
  {
    "employer": "IMAGEWORK TECHNOLOGIES CORPORATION",
    "state": "NY",
    "city": "WHITE PLAINS"
  },
  {
    "employer": "IMAGINAG TECH LLC",
    "state": "OH",
    "city": "CLEVELAND"
  },
  {
    "employer": "IMAGINATION THE AMERICAS INC",
    "state": "NY",
    "city": "NEW YORK"
  },
  {
    "employer": "IMAGING ASSOCIATES INC",
    "state": "MI",
    "city": "LIVONIA"
  },
  {
    "employer": "IMAGING ASSOCIATES OF NEW MEXICO LLC",
    "state": "CA",
    "city": "EL SEGUNDO"
  },
  {
    "employer": "IMAGRY INC",
    "state": "CA",
    "city": "SAN JOSE"
  },
  {
    "employer": "IMANAGE LLC",
    "state": "IL",
    "city": "CHICAGO"
  },
  {
    "employer": "IMAX CORPORATION",
    "state": "NY",
    "city": "NEW YORK"
  },
  {
    "employer": "IMBRIUM THERAPEUTICS LP",
    "state": "CT",
    "city": "STAMFORD"
  },
  {
    "employer": "IMBUESYS INC",
    "state": "IL",
    "city": "ROLLING MEADOWS"
  },
  {
    "employer": "IMC AMERICAS INC",
    "state": "IL",
    "city": "CHICAGO"
  },
  {
    "employer": "IMC MANAGER LLC",
    "state": "GA",
    "city": "ATLANTA"
  },
  {
    "employer": "IMCS GROUP INC",
    "state": "TX",
    "city": "IRVING"
  },
  {
    "employer": "IMD FLUID SYSTEM TECHNOLOGIES INC DBA SWAGELOK NORTHERN CALIFORNIA",
    "state": "CA",
    "city": "FREMONT"
  },
  {
    "employer": "IMDB.COM INC",
    "state": "VA",
    "city": "ARLINGTON"
  },
  {
    "employer": "IMEC USA NANOELECTRONICS DESIGN CENTER INC",
    "state": "FL",
    "city": "KISSIMMEE"
  },
  {
    "employer": "IMEG CORP",
    "state": "CA",
    "city": "PASADENA"
  },
  {
    "employer": "IMERYS PERFORMANCE MINERALS AMERICAS INC",
    "state": "GA",
    "city": "SUWANEE"
  },
  {
    "employer": "IMERYS USA INC",
    "state": "GA",
    "city": "ROSWELL"
  },
  {
    "employer": "IMETRIS CORPORATION",
    "state": "MI",
    "city": "SALINE"
  },
  {
    "employer": "IMG CONSULTING LLC",
    "state": "CA",
    "city": "IRVINE"
  },
  {
    "employer": "IMG REBEL ADVISORY INC",
    "state": "DC",
    "city": "WASHINGTON"
  },
  {
    "employer": "IMG SYSTEMS INC",
    "state": "TX",
    "city": "PLANO"
  },
  {
    "employer": "IMI HYDRONIC ENGINEERING INC",
    "state": "TX",
    "city": "DALLAS"
  },
  {
    "employer": "IMI INFRA SOLUTIONS LLC",
    "state": "FL",
    "city": "TAMPA"
  },
  {
    "employer": "IMI STUDIO CORP",
    "state": "",
    "city": ""
  },
  {
    "employer": "IMIDIA LLC",
    "state": "TX",
    "city": "CYPRESS"
  },
  {
    "employer": "IMINDS TECHNOLOGY SYSTEMS INC",
    "state": "PA",
    "city": "PITTSBURGH"
  },
  {
    "employer": "IMMENSE BRAINS LLC",
    "state": "CO",
    "city": "COLORADO SPRINGS"
  },
  {
    "employer": "IMMERSA INC",
    "state": "CA",
    "city": "PALO ALTO"
  },
  {
    "employer": "IMMERSED GAMES INC",
    "state": "NY",
    "city": "BUFFALO"
  }
]